pbr/__init__.py
pbr/builddoc.py
pbr/core.py
pbr/extra_files.py
pbr/find_package.py
pbr/git.py
pbr/options.py
pbr/packaging.py
pbr/pbr_json.py
pbr/pipfile.py
pbr/testr_command.py
pbr/toml.py
pbr/util.py
pbr/version.py
pbr/cmd/__init__.py
pbr/cmd/main.py
pbr/hooks/__init__.py
pbr/hooks/backwards.py
pbr/hooks/base.py
pbr/hooks/commands.py
pbr/hooks/files.py
pbr/hooks/metadata.py
pbr/tests/__init__.py
pbr/tests/base.py
pbr/tests/test_commands.py
pbr/tests/test_core.py
pbr/tests/test_files.py
pbr/tests/test_hooks.py
pbr/tests/test_integration.py
pbr/tests/test_packaging.py
pbr/tests/test_pbr_json.py
pbr/tests/test_setup.py
pbr/tests/test_util.py
pbr/tests/test_version.py
pbr/tests/test_wsgi.py
pbr/tests/util.py
pbr/tests/testpackage/CHANGES.txt
pbr/tests/testpackage/LICENSE.txt
pbr/tests/testpackage/MANIFEST.in
pbr/tests/testpackage/README.txt
pbr/tests/testpackage/extra-file.txt
pbr/tests/testpackage/git-extra-file.txt
pbr/tests/testpackage/setup.cfg
pbr/tests/testpackage/setup.py
pbr/tests/testpackage/test-requirements.txt
pbr/tests/testpackage/data_files/a.txt
pbr/tests/testpackage/data_files/b.txt
pbr/tests/testpackage/data_files/c.rst
pbr/tests/testpackage/doc/source/conf.py
pbr/tests/testpackage/doc/source/index.rst
pbr/tests/testpackage/doc/source/installation.rst
pbr/tests/testpackage/doc/source/usage.rst
pbr/tests/testpackage/pbr_testpackage/__init__.py
pbr/tests/testpackage/pbr_testpackage/_setup_hooks.py
pbr/tests/testpackage/pbr_testpackage/cmd.py
pbr/tests/testpackage/pbr_testpackage/extra.py
pbr/tests/testpackage/pbr_testpackage/wsgi.py
pbr/tests/testpackage/pbr_testpackage/package_data/1.txt
pbr/tests/testpackage/pbr_testpackage/package_data/2.txt
pbr/tests/testpackage/src/testext.c
pbr/tests/testpipfilepackage/Pipfile
pbr/tests/testpipfilepackage/README.txt
pbr/tests/testpipfilepackage/setup.cfg
pbr/tests/testpipfilepackage/setup.py
pbrlgs-3.1.4.dist-info/DESCRIPTION.rst
pbrlgs-3.1.4.dist-info/METADATA
pbrlgs-3.1.4.dist-info/RECORD
pbrlgs-3.1.4.dist-info/WHEEL
pbrlgs-3.1.4.dist-info/entry_points.txt
pbrlgs-3.1.4.dist-info/metadata.json
pbrlgs-3.1.4.dist-info/top_level.txt
